README.txt
setup.py
collective/__init__.py
collective.nextprev.egg-info/PKG-INFO
collective.nextprev.egg-info/SOURCES.txt
collective.nextprev.egg-info/dependency_links.txt
collective.nextprev.egg-info/entry_points.txt
collective.nextprev.egg-info/namespace_packages.txt
collective.nextprev.egg-info/not-zip-safe
collective.nextprev.egg-info/requires.txt
collective.nextprev.egg-info/top_level.txt
collective/nextprev/README.txt
collective/nextprev/__init__.py
collective/nextprev/configure.zcml
collective/nextprev/cookie.py
collective/nextprev/overrides.zcml
collective/nextprev/provider.py
collective/nextprev/results.py
collective/nextprev/testing.py
collective/nextprev/tests.py
collective/nextprev/topic.py
collective/nextprev/view.py
docs/HISTORY.txt
docs/TODO.txt