Metadata-Version: 1.0
Name: collective.nextprev
Version: 0.2
Summary: Next/Previous navigation through collection results
Home-page: http://pypi.python.org/pypi/collective.nextprev
Author: Ross Patterson
Author-email: me@rpatterson.net
License: GPL
Platform: UNKNOWN
Classifier: Programming Language :: Python
Classifier: Topic :: Software Development :: Libraries :: Python Modules
